waldiez_runner/__init__.py
waldiez_runner/__main__.py
waldiez_runner/_logging.py
waldiez_runner/_version.py
waldiez_runner/cli.py
waldiez_runner/main.py
waldiez_runner/py.typed
waldiez_runner/start.py
waldiez_runner/worker.py
waldiez_runner/client/__init__.py
waldiez_runner/client/_api_base.py
waldiez_runner/client/_clients_api.py
waldiez_runner/client/_tasks_api.py
waldiez_runner/client/_websockets.py
waldiez_runner/client/auth.py
waldiez_runner/client/client_base.py
waldiez_runner/client/clients_admin.py
waldiez_runner/client/models.py
waldiez_runner/client/tasks_client.py
waldiez_runner/config/__init__.py
waldiez_runner/config/_auth.py
waldiez_runner/config/_common.py
waldiez_runner/config/_postgres.py
waldiez_runner/config/_redis.py
waldiez_runner/config/_server.py
waldiez_runner/config/_tasks.py
waldiez_runner/config/settings.py
waldiez_runner/config/settings_manager.py
waldiez_runner/dependencies/__init__.py
waldiez_runner/dependencies/_utils.py
waldiez_runner/dependencies/auth.py
waldiez_runner/dependencies/context.py
waldiez_runner/dependencies/database.py
waldiez_runner/dependencies/getters.py
waldiez_runner/dependencies/jwks.py
waldiez_runner/dependencies/lifecycle.py
waldiez_runner/dependencies/redis.py
waldiez_runner/dependencies/storage/__init__.py
waldiez_runner/dependencies/storage/base.py
waldiez_runner/dependencies/storage/factory.py
waldiez_runner/dependencies/storage/local.py
waldiez_runner/dependencies/storage/utils/__init__.py
waldiez_runner/dependencies/storage/utils/_common.py
waldiez_runner/dependencies/storage/utils/_download.py
waldiez_runner/dependencies/storage/utils/_filename.py
waldiez_runner/hashing/__init__.py
waldiez_runner/hashing/_argon_hasher.py
waldiez_runner/hashing/_bcrypt_verifier.py
waldiez_runner/hashing/_scrypt_hasher.py
waldiez_runner/hashing/dispatcher.py
waldiez_runner/hashing/protocol.py
waldiez_runner/middleware/__init__.py
waldiez_runner/middleware/conditional_gzip.py
waldiez_runner/middleware/extra_headers.py
waldiez_runner-0.7.1.dist-info/METADATA
waldiez_runner-0.7.1.dist-info/WHEEL
waldiez_runner-0.7.1.dist-info/entry_points.txt
waldiez_runner-0.7.1.dist-info/licenses/LICENSE
waldiez_runner-0.7.1.dist-info/licenses/NOTICE.md
waldiez_runner-0.7.1.dist-info/RECORD
