Metadata-Version: 2.4
Name: waldiez_runner
Version: 0.7.1
Summary: Serve and run your Waldiez flows in isolated environments and stream logs/input/output via Redis
Project-URL: homepage, https://github.com/waldiez/runner.git
Project-URL: repository, https://github.com/waldiez/runner.git
Author-email: Panagiotis Kasnesis <pkasnesis@waldiez.io>, Lazaros Toumanidis <laztoum@waldiez.io>, Christos Chatzigeorgiou <chrihatz@waldiez.io>
License-File: LICENSE
License-File: NOTICE.md
Classifier: Development Status :: 4 - Beta
Classifier: Intended Audience :: Developers
Classifier: Intended Audience :: Science/Research
Classifier: License :: OSI Approved :: Apache Software License
Classifier: Operating System :: OS Independent
Classifier: Programming Language :: Python
Classifier: Programming Language :: Python :: 3
Classifier: Programming Language :: Python :: 3.11
Classifier: Programming Language :: Python :: 3.12
Classifier: Programming Language :: Python :: 3.13
Classifier: Programming Language :: Python :: 3.14
Requires-Python: >=3.11
Requires-Dist: aiocsv==1.4.0
Requires-Dist: aiofiles==25.1.0
Requires-Dist: aioftp==0.27.2
Requires-Dist: aiohttp==3.13.3
Requires-Dist: aiosqlite>=0.22.0
Requires-Dist: alembic==1.18.0
Requires-Dist: anyio==4.12.1
Requires-Dist: argon2-cffi==25.1.0
Requires-Dist: asyncssh==2.22.0
Requires-Dist: bcrypt==5.0.0
Requires-Dist: boto3==1.42.26
Requires-Dist: fakeredis==2.33.0
Requires-Dist: fastapi-pagination==0.15.6
Requires-Dist: fastapi[all]==0.128.0
Requires-Dist: faststream[cli,redis]==0.6.5
Requires-Dist: hiredis==3.3.0
Requires-Dist: httpx<1
Requires-Dist: nest-asyncio==1.6.0
Requires-Dist: orjson==3.11.5
Requires-Dist: psutil>=7.1.3
Requires-Dist: psycopg>=3.3.2; sys_platform == 'win32' and platform_machine == 'AARCH64'
Requires-Dist: psycopg>=3.3.2; sys_platform == 'win32' and platform_machine == 'ARM64'
Requires-Dist: psycopg>=3.3.2; sys_platform == 'win32' and platform_machine == 'aarch64'
Requires-Dist: psycopg>=3.3.2; sys_platform == 'win32' and platform_machine == 'arm64'
Requires-Dist: psycopg[binary,pool]>=3.3.2; sys_platform == 'darwin'
Requires-Dist: psycopg[binary,pool]>=3.3.2; sys_platform == 'linux'
Requires-Dist: psycopg[binary,pool]>=3.3.2; sys_platform == 'win32' and platform_machine != 'arm64' and platform_machine != 'ARM64' and platform_machine != 'aarch64' and platform_machine != 'AARCH64'
Requires-Dist: puremagic==1.30
Requires-Dist: pydantic-settings==2.12.0
Requires-Dist: pydantic>=2.10
Requires-Dist: pyjwt[crypto]==2.10.1
Requires-Dist: pysqlite3-binary==0.5.4; sys_platform == 'linux' and platform_machine != 'arm64' and platform_machine != 'aarch64' and platform_machine != 'ARM64' and platform_machine != 'AARCH64'
Requires-Dist: python-dotenv==1.2.1
Requires-Dist: python-multipart==0.0.21
Requires-Dist: python-ulid==3.1.0
Requires-Dist: redis>=6.4.0
Requires-Dist: slowapi==0.1.9
Requires-Dist: taskiq-dependencies==1.5.7
Requires-Dist: taskiq-redis==1.2.1
Requires-Dist: taskiq==0.12.1
Requires-Dist: tenacity<10.0.0
Requires-Dist: trio==0.32.0
Requires-Dist: typer<1,>=0.18.0
Requires-Dist: uvicorn[standard]==0.40.0
Requires-Dist: uvloop==0.22.1; sys_platform != 'win32'
Requires-Dist: virtualenv==20.36.1
Requires-Dist: waldiez==0.7.1
Requires-Dist: zipstream==1.1.4
Provides-Extra: dev
Requires-Dist: autoflake==2.3.1; extra == 'dev'
Requires-Dist: bandit==1.9.2; extra == 'dev'
Requires-Dist: basedpyright==1.37.1; extra == 'dev'
Requires-Dist: black[jupyter]==25.12.0; extra == 'dev'
Requires-Dist: flake8==7.3.0; extra == 'dev'
Requires-Dist: hatchling==1.28.0; extra == 'dev'
Requires-Dist: isort==7.0.0; extra == 'dev'
Requires-Dist: locust==2.43.1; extra == 'dev'
Requires-Dist: lupa==2.6; extra == 'dev'
Requires-Dist: mypy==1.19.1; extra == 'dev'
Requires-Dist: prek==0.2.27; extra == 'dev'
Requires-Dist: pydocstyle==6.3.0; extra == 'dev'
Requires-Dist: pylint==4.0.4; extra == 'dev'
Requires-Dist: ruff==0.14.11; extra == 'dev'
Requires-Dist: streamlit-autorefresh==1.0.1; extra == 'dev'
Requires-Dist: streamlit==1.52.2; extra == 'dev'
Requires-Dist: types-aiofiles==25.1.0.20251011; extra == 'dev'
Requires-Dist: types-psutil==7.2.1.20251231; extra == 'dev'
Requires-Dist: types-pyyaml==6.0.12.20250915; extra == 'dev'
Requires-Dist: types-redis==4.6.0.20241004; extra == 'dev'
Requires-Dist: types-requests==2.32.4.20260107; extra == 'dev'
Requires-Dist: types-toml==0.10.8.20240310; extra == 'dev'
Requires-Dist: yamllint==1.38.0; extra == 'dev'
Provides-Extra: docs
Requires-Dist: mdx-include==1.4.2; extra == 'docs'
Requires-Dist: mdx-truly-sane-lists==1.3; extra == 'docs'
Requires-Dist: mkdocs-jupyter==0.25.1; extra == 'docs'
Requires-Dist: mkdocs-macros-plugin==1.5.0; extra == 'docs'
Requires-Dist: mkdocs-material==9.7.1; extra == 'docs'
Requires-Dist: mkdocs-mermaid2-plugin==1.2.3; extra == 'docs'
Requires-Dist: mkdocs-minify-html-plugin; (python_version >= '3.13' and sys_platform == 'win32' and platform_machine == 'AARCH64') and extra == 'docs'
Requires-Dist: mkdocs-minify-html-plugin; (python_version >= '3.13' and sys_platform == 'win32' and platform_machine == 'ARM64') and extra == 'docs'
Requires-Dist: mkdocs-minify-html-plugin; (python_version >= '3.13' and sys_platform == 'win32' and platform_machine == 'aarch64') and extra == 'docs'
Requires-Dist: mkdocs-minify-html-plugin; (python_version >= '3.13' and sys_platform == 'win32' and platform_machine == 'arm64') and extra == 'docs'
Requires-Dist: mkdocs-minify-html-plugin==0.3.9; (python_version < '3.13') and extra == 'docs'
Requires-Dist: mkdocs-minify-html-plugin==0.3.9; (python_version >= '3.13' and sys_platform != 'win32') and extra == 'docs'
Requires-Dist: mkdocs-minify-html-plugin==0.3.9; (python_version >= '3.13' and sys_platform == 'win32' and platform_machine != 'arm64' and platform_machine != 'aarch64' and platform_machine != 'ARM64' and platform_machine != 'AARCH64') and extra == 'docs'
Requires-Dist: mkdocs==1.6.1; extra == 'docs'
Requires-Dist: mkdocstrings-crystal==0.3.9; extra == 'docs'
Requires-Dist: mkdocstrings-python==2.0.1; extra == 'docs'
Requires-Dist: mkdocstrings[crystal,python]==1.0.0; extra == 'docs'
Requires-Dist: neoteroi-mkdocs==1.2.0; extra == 'docs'
Provides-Extra: test
Requires-Dist: asgi-lifespan==2.1.0; extra == 'test'
Requires-Dist: greenlet==3.3.0; extra == 'test'
Requires-Dist: httpx-ws==0.8.2; extra == 'test'
Requires-Dist: httpx<1; extra == 'test'
Requires-Dist: locust==2.43.1; extra == 'test'
Requires-Dist: lupa==2.6; extra == 'test'
Requires-Dist: moto[s3]==5.1.19; extra == 'test'
Requires-Dist: pytest-asyncio==1.3.0; extra == 'test'
Requires-Dist: pytest-cov==7.0.0; extra == 'test'
Requires-Dist: pytest-env==1.2.0; extra == 'test'
Requires-Dist: pytest-html==4.1.1; extra == 'test'
Requires-Dist: pytest-httpx; extra == 'test'
Requires-Dist: pytest-mock==3.15.1; extra == 'test'
Requires-Dist: pytest-sugar==1.1.1; extra == 'test'
Requires-Dist: pytest-timeout==2.4.0; extra == 'test'
Requires-Dist: pytest-xdist==3.8.0; extra == 'test'
Requires-Dist: pytest>=8.4.2; extra == 'test'
